MANIFEST.in
README
setup.py
heightfield/__init__.py
heightfield/deposition.py
heightfield/gl.py
heightfield/main.py
heightfield/surface.py
heightfield.egg-info/PKG-INFO
heightfield.egg-info/SOURCES.txt
heightfield.egg-info/dependency_links.txt
heightfield.egg-info/entry_points.txt
heightfield.egg-info/requires.txt
heightfield.egg-info/top_level.txt
heightfield/data/heightmap.png
heightfield/viewer/__init__.py
heightfield/viewer/pygameviewer.py