Metadata-Version: 1.0
Name: heightfield
Version: 0.2
Summary: Generate random maps by particle deposition
Home-page: https://bitbucket.org/lordmauve/heightfield
Author: Daniel Pope / Reading Python Dojo
Author-email: lord.mauve@gmail.com
License: LGPL
Platform: UNKNOWN
Classifier: Development Status :: 2 - Pre-Alpha
Classifier: Environment :: Console
Classifier: Intended Audience :: Developers
Classifier: License :: OSI Approved :: GNU Library or Lesser General Public License (LGPL)
Classifier: Operating System :: OS Independent
Classifier: Topic :: Multimedia :: Graphics
